factorium/__init__.py
factorium/aggbar.py
factorium/constants.py
factorium/backtest/__init__.py
factorium/backtest/backtester.py
factorium/backtest/constraints.py
factorium/backtest/metrics.py
factorium/backtest/portfolio.py
factorium/backtest/utils.py
factorium/backtest/vectorized.py
factorium/data/__init__.py
factorium/data/aggregator.py
factorium/data/cache.py
factorium/data/downloader.py
factorium/data/loader.py
factorium/data/metadata.py
factorium/data/parquet.py
factorium/data/adapters/__init__.py
factorium/data/adapters/base.py
factorium/data/adapters/binance.py
factorium/factors/__init__.py
factorium/factors/analyzer.py
factorium/factors/base.py
factorium/factors/composite.py
factorium/factors/core.py
factorium/factors/engine.py
factorium/factors/evaluation.py
factorium/factors/operators.py
factorium/factors/parser.py
factorium/factors/plotting.py
factorium/factors/plotting_analyzer.py
factorium/factors/mixins/__init__.py
factorium/factors/mixins/cs_ops.py
factorium/factors/mixins/math_ops.py
factorium/factors/mixins/ts_ops.py
factorium/research/__init__.py
factorium/research/report.py
factorium/research/session.py
factorium-0.3.1.dist-info/METADATA
factorium-0.3.1.dist-info/WHEEL
factorium-0.3.1.dist-info/licenses/LICENSE
factorium-0.3.1.dist-info/RECORD
