Metadata-Version: 2.4
Name: factorium
Version: 0.3.1
Summary: A quantitative factor analysis library for financial research
Author: Samuel Chang
License: MIT
License-File: LICENSE
Keywords: factor,finance,quantitative,research,trading
Classifier: Development Status :: 3 - Alpha
Classifier: Intended Audience :: Financial and Insurance Industry
Classifier: Intended Audience :: Science/Research
Classifier: License :: OSI Approved :: MIT License
Classifier: Programming Language :: Python :: 3
Classifier: Programming Language :: Python :: 3.11
Classifier: Programming Language :: Python :: 3.12
Classifier: Programming Language :: Python :: 3.13
Classifier: Topic :: Office/Business :: Financial :: Investment
Classifier: Topic :: Scientific/Engineering :: Information Analysis
Requires-Python: >=3.11
Requires-Dist: aiofiles>=23.0.0
Requires-Dist: aiohttp>=3.9.0
Requires-Dist: duckdb>=1.0.0
Requires-Dist: matplotlib>=3.7.0
Requires-Dist: numba>=0.57.0
Requires-Dist: numpy>=1.24.0
Requires-Dist: pandas>=2.0.0
Requires-Dist: polars>=1.0.0
Requires-Dist: pyarrow>=14.0.0
Requires-Dist: pyparsing>=3.0.0
Requires-Dist: scipy>=1.10.0
Provides-Extra: dev
Requires-Dist: mypy>=1.0.0; extra == 'dev'
Requires-Dist: pytest-cov>=4.0.0; extra == 'dev'
Requires-Dist: pytest>=7.0.0; extra == 'dev'
Requires-Dist: ruff>=0.1.0; extra == 'dev'
Provides-Extra: jupyter
Requires-Dist: nest-asyncio>=1.5.0; extra == 'jupyter'
